{
"meta":{"launch_mode":"Train","name":"experiment","iteration_count":20,"learn_metrics":[{"best_value":"Min","name":"RMSE"}],"test_sets":[],"test_metrics":[],"learn_sets":["learn"]},
"iterations":[
{"learn":[0.295769088],"iteration":0,"passed_time":0.07393576598,"remaining_time":1.404779554},
{"learn":[0.288980453],"iteration":1,"passed_time":0.08484653349,"remaining_time":0.7636188014},
{"learn":[0.2823883137],"iteration":2,"passed_time":0.0959555061,"remaining_time":0.5437478679},
{"learn":[0.2761822914],"iteration":3,"passed_time":0.1128018674,"remaining_time":0.4512074695},
{"learn":[0.2700780284],"iteration":4,"passed_time":0.127752109,"remaining_time":0.3832563269},
{"learn":[0.26420721],"iteration":5,"passed_time":0.1429323588,"remaining_time":0.3335088373},
{"learn":[0.258519603],"iteration":6,"passed_time":0.1694700249,"remaining_time":0.3147300462},
{"learn":[0.2530196088],"iteration":7,"passed_time":0.1825869098,"remaining_time":0.2738803648},
{"learn":[0.2479257183],"iteration":8,"passed_time":0.2048149076,"remaining_time":0.2503293316},
{"learn":[0.2427811526],"iteration":9,"passed_time":0.2210737664,"remaining_time":0.2210737664},
{"learn":[0.2380002458],"iteration":10,"passed_time":0.2362040489,"remaining_time":0.1932578582},
{"learn":[0.2333474912],"iteration":11,"passed_time":0.2485706125,"remaining_time":0.1657137417},
{"learn":[0.2288560042],"iteration":12,"passed_time":0.2595664881,"remaining_time":0.1397665705},
{"learn":[0.2244889142],"iteration":13,"passed_time":0.2724529549,"remaining_time":0.1167655521},
{"learn":[0.2202543436],"iteration":14,"passed_time":0.290808366,"remaining_time":0.09693612201},
{"learn":[0.2162670513],"iteration":15,"passed_time":0.3082238501,"remaining_time":0.07705596251},
{"learn":[0.2125152124],"iteration":16,"passed_time":0.3368956423,"remaining_time":0.05945217217},
{"learn":[0.2088786671],"iteration":17,"passed_time":0.3561340515,"remaining_time":0.03957045017},
{"learn":[0.2054409223],"iteration":18,"passed_time":0.3738285068,"remaining_time":0.01967518457},
{"learn":[0.2020012791],"iteration":19,"passed_time":0.384371352,"remaining_time":0}
]}